MANIFEST.in
setup.cfg
setup.py
versioneer.py
pyannote_workflows/__init__.py
pyannote_workflows/_version.py
pyannote_workflows/utils.py
pyannote_workflows.egg-info/PKG-INFO
pyannote_workflows.egg-info/SOURCES.txt
pyannote_workflows.egg-info/dependency_links.txt
pyannote_workflows.egg-info/pbr.json
pyannote_workflows.egg-info/top_level.txt
pyannote_workflows/tasks/__init__.py
pyannote_workflows/tasks/evaluation.py
pyannote_workflows/tasks/face.py
pyannote_workflows/tasks/speech.py
pyannote_workflows/tasks/tvd_dataset.py
pyannote_workflows/workflows/__init__.py
pyannote_workflows/workflows/sub_sad.py
pyannote_workflows/workflows/sub_sad_bis.py